climify_api/ApiController.py
climify_api/REST.py
climify_api/__init__.py
climify_api/api_client.py
climify_api/auth.py
climify_api/configuration.py
climify_api/exceptions.py
climify_api/schemas.py
climify_api/apis/PathBase.py
climify_api/apis/__init__.py
climify_api/apis/v1/ApiController.py
climify_api/apis/v1/__init__.py
climify_api/apis/v1/paths/__init__.py
climify_api/apis/v1/paths/buildings_id/__init__.py
climify_api/apis/v1/paths/buildings_id/get.py
climify_api/apis/v1/paths/buildings_id_devices/__init__.py
climify_api/apis/v1/paths/buildings_id_devices/get.py
climify_api/apis/v1/paths/buildings_id_metering_points/__init__.py
climify_api/apis/v1/paths/buildings_id_metering_points/get.py
climify_api/apis/v1/paths/devices_id/__init__.py
climify_api/apis/v1/paths/devices_id/get.py
climify_api/apis/v1/paths/feedback_forms_id_locations_id_responses/__init__.py
climify_api/apis/v1/paths/feedback_forms_id_locations_id_responses/get.py
climify_api/apis/v1/paths/locations_id/__init__.py
climify_api/apis/v1/paths/locations_id/get.py
climify_api/apis/v1/paths/locations_id_change_temperature/__init__.py
climify_api/apis/v1/paths/locations_id_change_temperature/post.py
climify_api/apis/v1/paths/locations_id_devices/__init__.py
climify_api/apis/v1/paths/locations_id_devices/get.py
climify_api/apis/v1/paths/locations_id_sensor_values/__init__.py
climify_api/apis/v1/paths/locations_id_sensor_values/get.py
climify_api/apis/v1/paths/maps_id/__init__.py
climify_api/apis/v1/paths/maps_id/get.py
climify_api/apis/v1/paths/maps_id_devices/__init__.py
climify_api/apis/v1/paths/maps_id_devices/get.py
climify_api/apis/v1/paths/metering_points_id/__init__.py
climify_api/apis/v1/paths/metering_points_id/get.py
climify_api/apis/v1/paths/organisations_id/__init__.py
climify_api/apis/v1/paths/organisations_id/get.py
climify_api/apis/v1/paths/organisations_id_devices/__init__.py
climify_api/apis/v1/paths/organisations_id_devices/get.py
climify_api/apis/v1/paths/resources/__init__.py
climify_api-1.0.39.dist-info/licenses/LICENSE
climify_api-1.0.39.dist-info/METADATA
climify_api-1.0.39.dist-info/WHEEL
climify_api-1.0.39.dist-info/top_level.txt
climify_api-1.0.39.dist-info/RECORD
