Metadata-Version: 2.4
Name: climify_api
Version: 1.0.39
Summary: A wrapper library for the Climify REST API
Author-email: Climify Aps <info@climify.com>
Project-URL: Homepage, https://gitlab.climify.com/climify/python-api-lib
Project-URL: Issues, https://gitlab.climify.com/climify/python-api-lib/-/issues
Keywords: Climify,Environmental engineering
Classifier: Development Status :: 2 - Pre-Alpha
Classifier: Intended Audience :: Science/Research
Classifier: Intended Audience :: Developers
Classifier: Topic :: Scientific/Engineering
Classifier: Topic :: Software Development :: Libraries
Classifier: Programming Language :: Python :: 3
Classifier: License :: OSI Approved :: MIT License
Classifier: Operating System :: OS Independent
Requires-Python: >=3.7
License-File: LICENSE
Requires-Dist: certifi>=14.5.14
Requires-Dist: frozendict>=2.3.4
Requires-Dist: python-dateutil
Requires-Dist: typing_extensions>=4.3.0
Requires-Dist: urllib3>=1.26.7
Requires-Dist: requests
Requires-Dist: requests-oauthlib
Requires-Dist: pyyaml
Requires-Dist: oauthlib
Requires-Dist: varname==0.13.5
Requires-Dist: pydantic>2.0.0
Requires-Dist: pandas
Dynamic: license-file
